stencil.py
stencil_template-4.2.3.dist-info/LICENSE
stencil_template-4.2.3.dist-info/METADATA
stencil_template-4.2.3.dist-info/WHEEL
stencil_template-4.2.3.dist-info/top_level.txt
stencil_template-4.2.3.dist-info/RECORD
