Metadata-Version: 2.1
Name: stencil-template
Version: 4.2.3
Summary: A template engine light enough to embed in your project.
Author-email: Curtis Maloney <curtis@tinbrain.net>
License: MIT
Project-URL: Repository, https://github.com/funkybob/stencil/
Project-URL: Documentation, https://stencil-templates.readthedocs.io/en/latest/
Keywords: template
Classifier: Development Status :: 5 - Production/Stable
Classifier: Intended Audience :: Developers
Classifier: Programming Language :: Python :: 3
License-File: LICENSE
Provides-Extra: test
Requires-Dist: ruff ; extra == 'test'
Requires-Dist: pytest ; extra == 'test'
Requires-Dist: coverage ; extra == 'test'
